bob/__init__.py
bob/bio/__init__.py
bob/bio/face/__init__.py
bob/bio/face/color.py
bob/bio/face/utils.py
bob/bio/face/annotator/Base.py
bob/bio/face/annotator/__init__.py
bob/bio/face/annotator/faceX_106landmarks.py
bob/bio/face/annotator/mtcnn.py
bob/bio/face/annotator/tinyface.py
bob/bio/face/annotator/utils.py
bob/bio/face/config/__init__.py
bob/bio/face/config/annotator/__init__.py
bob/bio/face/config/annotator/mtcnn.py
bob/bio/face/config/annotator/tinyface.py
bob/bio/face/config/baseline/__init__.py
bob/bio/face/config/baseline/afffe.py
bob/bio/face/config/baseline/arcface_insightface.py
bob/bio/face/config/baseline/attention_net.py
bob/bio/face/config/baseline/dummy.py
bob/bio/face/config/baseline/efficient_net.py
bob/bio/face/config/baseline/facenet_sanderberg.py
bob/bio/face/config/baseline/ghost_net.py
bob/bio/face/config/baseline/hr_net.py
bob/bio/face/config/baseline/inception_resnetv1_casiawebface.py
bob/bio/face/config/baseline/inception_resnetv1_msceleb.py
bob/bio/face/config/baseline/inception_resnetv2_casiawebface.py
bob/bio/face/config/baseline/inception_resnetv2_msceleb.py
bob/bio/face/config/baseline/iresnet100.py
bob/bio/face/config/baseline/iresnet100_elastic.py
bob/bio/face/config/baseline/iresnet100_msceleb_arcface_20210623.py
bob/bio/face/config/baseline/iresnet34.py
bob/bio/face/config/baseline/iresnet50.py
bob/bio/face/config/baseline/iresnet50_msceleb_arcface_20210623.py
bob/bio/face/config/baseline/mobile_facenet.py
bob/bio/face/config/baseline/mobilenetv2_msceleb_arcface_2021.py
bob/bio/face/config/baseline/oxford_resnet50_ft_dag_vgg2.py
bob/bio/face/config/baseline/oxford_resnet50_scratch_dag_vgg2.py
bob/bio/face/config/baseline/oxford_senet50_ft_dag_vgg2.py
bob/bio/face/config/baseline/oxford_senet50_scratch_dag_vgg2.py
bob/bio/face/config/baseline/resne_st.py
bob/bio/face/config/baseline/resnet.py
bob/bio/face/config/baseline/resnet101_msceleb_arcface_20210521.py
bob/bio/face/config/baseline/resnet50_msceleb_arcface_2021.py
bob.bio.face-8.0.1.dist-info/LICENSE
bob.bio.face-8.0.1.dist-info/METADATA
bob.bio.face-8.0.1.dist-info/WHEEL
bob.bio.face-8.0.1.dist-info/entry_points.txt
bob.bio.face-8.0.1.dist-info/top_level.txt
bob.bio.face-8.0.1.dist-info/RECORD
