Metadata-Version: 2.1
Name: bob.bio.face
Version: 8.0.1
Summary: Tools for running face recognition experiments
Author-email: Manuel Gunther <siebenkopf@googlemail.com>
License: BSD 3-Clause License
Project-URL: documentation, https://www.idiap.ch/software/bob/docs/bob/bob.bio.face/v8.0.1/sphinx/
Project-URL: homepage, https://pypi.org/project/bob.bio.face/
Project-URL: repository, https://gitlab.idiap.ch/bob/bob.bio.face
Project-URL: changelog, https://gitlab.idiap.ch/bob/bob.bio.face/-/releases
Keywords: bob,biometric recognition,evaluation
Classifier: Framework :: Bob
Classifier: Development Status :: 3 - Alpha
Classifier: Intended Audience :: Developers
Classifier: License :: OSI Approved :: BSD License
Classifier: Natural Language :: English
Classifier: Programming Language :: Python
Classifier: Topic :: Scientific/Engineering :: Artificial Intelligence
Requires-Python: >=3.9
License-File: LICENSE
Requires-Dist: bob ==12.1.1
Requires-Dist: bob.io.base ==5.1.1
Requires-Dist: bob.measure ==6.1.1
Requires-Dist: bob.bio.base ==8.1.1
Requires-Dist: bob.pipelines ==4.0.1
Requires-Dist: clapper ~=1.0
Requires-Dist: imageio-ffmpeg ~=0.4
Requires-Dist: matplotlib ~=3.8
Requires-Dist: opencv-python ~=4.9
Requires-Dist: pytorch-lightning ~=2.2
Requires-Dist: scikit-image ~=0.19
Requires-Dist: scikit-learn ~=1.4
Requires-Dist: torch ~=2.1
Requires-Dist: torchvision ~=0.14
Requires-Dist: aiohttp ~=3.9
Provides-Extra: doc
Requires-Dist: sphinx ; extra == 'doc'
Requires-Dist: sphinx-rtd-theme ; extra == 'doc'
Requires-Dist: sphinx-autodoc-typehints ; extra == 'doc'
Requires-Dist: auto-intersphinx ; extra == 'doc'
Requires-Dist: sphinxcontrib-programoutput ; extra == 'doc'
Requires-Dist: matplotlib ; extra == 'doc'
Requires-Dist: dask-ml ; extra == 'doc'
Requires-Dist: tensorflow ; extra == 'doc'
Provides-Extra: qa
Requires-Dist: pre-commit ; extra == 'qa'
Provides-Extra: test
Requires-Dist: pytest ; extra == 'test'
Requires-Dist: pytest-cov ; extra == 'test'
Requires-Dist: coverage ; extra == 'test'
Requires-Dist: dask ; extra == 'test'
Requires-Dist: tensorflow ; extra == 'test'
